[
  {
    "file": "Fake Test Data.xlsx [X12 - 278]",
    "detections": [
      {
        "label": "PHONE",
        "box": [
          0,
          0,
          0,
          0
        ],
        "matched": "46\n9968776055"
      },
      {
        "label": "NPI",
        "box": [
          205,
          174,
          90,
          8
        ],
        "matched": "9968776055"
      },
      {
        "label": "DL_GENERIC",
        "box": [
          81,
          74,
          73,
          30
        ],
        "matched": "THERAPYCLINIC"
      },
      {
        "label": "DL_GENERIC",
        "box": [
          191,
          74,
          35,
          30
        ],
        "matched": "THPLAN"
      },
      {
        "label": "DL_GENERIC",
        "box": [
          233,
          74,
          53,
          30
        ],
        "matched": "20250723"
      },
      {
        "label": "DL_GENERIC",
        "box": [
          119,
          118,
          33,
          30
        ],
        "matched": "456789"
      },
      {
        "label": "DL_GENERIC",
        "box": [
          205,
          174,
          90,
          8
        ],
        "matched": "9968776055"
      },
      {
        "label": "DL_GENERIC",
        "box": [
          187,
          218,
          103,
          8
        ],
        "matched": "SCL123456789"
      },
      {
        "label": "DL_GENERIC",
        "box": [
          64,
          250,
          53,
          30
        ],
        "matched": "BANGALORE"
      },
      {
        "label": "CVV",
        "box": [
          85,
          64,
          22,
          8
        ],
        "matched": "400"
      },
      {
        "label": "BANK_ACC",
        "box": [
          205,
          174,
          90,
          8
        ],
        "matched": "9968776055"
      },
      {
        "label": "BANK_ACC",
        "box": [
          187,
          218,
          103,
          8
        ],
        "matched": "123456789"
      },
      {
        "label": "ADDRESS",
        "box": [
          311,
          548,
          37,
          9
        ],
        "matched": "Address"
      }
    ],
    "redacted": [
      {
        "label": "PHONE",
        "box": [
          0,
          0,
          0,
          0
        ],
        "matched": "46\n9968776055"
      },
      {
        "label": "NPI",
        "box": [
          205,
          174,
          90,
          8
        ],
        "matched": "9968776055"
      },
      {
        "label": "DL_GENERIC",
        "box": [
          81,
          74,
          73,
          30
        ],
        "matched": "THERAPYCLINIC"
      },
      {
        "label": "DL_GENERIC",
        "box": [
          191,
          74,
          35,
          30
        ],
        "matched": "THPLAN"
      },
      {
        "label": "DL_GENERIC",
        "box": [
          233,
          74,
          53,
          30
        ],
        "matched": "20250723"
      },
      {
        "label": "DL_GENERIC",
        "box": [
          119,
          118,
          33,
          30
        ],
        "matched": "456789"
      },
      {
        "label": "DL_GENERIC",
        "box": [
          205,
          174,
          90,
          8
        ],
        "matched": "9968776055"
      },
      {
        "label": "DL_GENERIC",
        "box": [
          187,
          218,
          103,
          8
        ],
        "matched": "SCL123456789"
      },
      {
        "label": "DL_GENERIC",
        "box": [
          64,
          250,
          53,
          30
        ],
        "matched": "BANGALORE"
      },
      {
        "label": "CVV",
        "box": [
          85,
          64,
          22,
          8
        ],
        "matched": "400"
      },
      {
        "label": "BANK_ACC",
        "box": [
          205,
          174,
          90,
          8
        ],
        "matched": "9968776055"
      },
      {
        "label": "BANK_ACC",
        "box": [
          187,
          218,
          103,
          8
        ],
        "matched": "123456789"
      },
      {
        "label": "ADDRESS",
        "box": [
          311,
          548,
          37,
          9
        ],
        "matched": "Address"
      }
    ],
    "mode": "blur",
    "timestamp": "20250903T121446",
    "page": ""
  },
  {
    "file": "Fake Test Data.xlsx [Fake Member ID & NPI]",
    "detections": [
      {
        "label": "PHONE",
        "box": [
          241,
          74,
          81,
          31
        ],
        "matched": "2345676611"
      },
      {
        "label": "PHONE",
        "box": [
          398,
          118,
          162,
          30
        ],
        "matched": "1164952208"
      },
      {
        "label": "PHONE",
        "box": [
          402,
          272,
          162,
          30
        ],
        "matched": "1578706308"
      },
      {
        "label": "PHONE",
        "box": [
          402,
          306,
          161,
          8
        ],
        "matched": "1104123801"
      },
      {
        "label": "NPI",
        "box": [
          398,
          118,
          162,
          30
        ],
        "matched": "1164952208"
      },
      {
        "label": "NPI",
        "box": [
          402,
          272,
          162,
          30
        ],
        "matched": "1578706308"
      },
      {
        "label": "NPI",
        "box": [
          402,
          306,
          161,
          8
        ],
        "matched": "1104123801"
      },
      {
        "label": "DL_GENERIC",
        "box": [
          90,
          63,
          40,
          11
        ],
        "matched": "BCBSAK"
      },
      {
        "label": "DL_GENERIC",
        "box": [
          134,
          64,
          71,
          8
        ],
        "matched": "123456789"
      },
      {
        "label": "DL_GENERIC",
        "box": [
          104,
          74,
          38,
          31
        ],
        "matched": "BOBSAR"
      },
      {
        "label": "DL_GENERIC",
        "box": [
          241,
          74,
          81,
          31
        ],
        "matched": "XOM2345676611"
      },
      {
        "label": "DL_GENERIC",
        "box": [
          551,
          74,
          55,
          31
        ],
        "matched": "184150458"
      },
      {
        "label": "DL_GENERIC",
        "box": [
          97,
          96,
          30,
          30
        ],
        "matched": "BCBSFL"
      },
      {
        "label": "DL_GENERIC",
        "box": [
          222,
          96,
          68,
          30
        ],
        "matched": "XJBH12345678"
      },
      {
        "label": "DL_GENERIC",
        "box": [
          87,
          129,
          65,
          11
        ],
        "matched": "BCBSID"
      },
      {
        "label": "DL_GENERIC",
        "box": [
          131,
          129,
          74,
          11
        ],
        "matched": "XNE123456789"
      },
      {
        "label": "DL_GENERIC",
        "box": [
          209,
          130,
          74,
          8
        ],
        "matched": "SAW123456789"
      },
      {
        "label": "DL_GENERIC",
        "box": [
          398,
          118,
          162,
          30
        ],
        "matched": "1164952208"
      },
      {
        "label": "DL_GENERIC",
        "box": [
          92,
          151,
          63,
          11
        ],
        "matched": "BCBSIL"
      },
      {
        "label": "DL_GENERIC",
        "box": [
          54,
          174,
          49,
          8
        ],
        "matched": "MICHIGAN"
      },
      {
        "label": "DL_GENERIC",
        "box": [
          238,
          174,
          74,
          8
        ],
        "matched": "FMMO123456789"
      },
      {
        "label": "DL_GENERIC",
        "box": [
          102,
          196,
          39,
          8
        ],
        "matched": "BCESMT"
      },
      {
        "label": "DL_GENERIC",
        "box": [
          114,
          239,
          41,
          11
        ],
        "matched": "BOBSOK"
      },
      {
        "label": "DL_GENERIC",
        "box": [
          159,
          240,
          75,
          9
        ],
        "matched": "YUPT23456789"
      },
      {
        "label": "DL_GENERIC",
        "box": [
          238,
          240,
          71,
          8
        ],
        "matched": "YUAI23456789"
      },
      {
        "label": "DL_GENERIC",
        "box": [
          55,
          261,
          44,
          11
        ],
        "matched": "OREGON"
      },
      {
        "label": "DL_GENERIC",
        "box": [
          154,
          262,
          78,
          9
        ],
        "matched": "WCP123456789"
      },
      {
        "label": "DL_GENERIC",
        "box": [
          93,
          283,
          40,
          11
        ],
        "matched": "BOBSTX"
      },
      {
        "label": "DL_GENERIC",
        "box": [
          217,
          284,
          70,
          8
        ],
        "matched": "JEA123456789"
      },
      {
        "label": "DL_GENERIC",
        "box": [
          402,
          272,
          162,
          30
        ],
        "matched": "1578706308"
      },
      {
        "label": "DL_GENERIC",
        "box": [
          89,
          305,
          41,
          11
        ],
        "matched": "BOBSUT"
      },
      {
        "label": "DL_GENERIC",
        "box": [
          134,
          306,
          77,
          9
        ],
        "matched": "128456789"
      },
      {
        "label": "DL_GENERIC",
        "box": [
          402,
          306,
          161,
          8
        ],
        "matched": "1104123801"
      },
      {
        "label": "BANK_ACC",
        "box": [
          134,
          64,
          71,
          8
        ],
        "matched": "123456789"
      },
      {
        "label": "BANK_ACC",
        "box": [
          241,
          74,
          81,
          31
        ],
        "matched": "2345676611"
      },
      {
        "label": "BANK_ACC",
        "box": [
          551,
          74,
          55,
          31
        ],
        "matched": "184150458"
      },
      {
        "label": "BANK_ACC",
        "box": [
          134,
          64,
          71,
          8
        ],
        "matched": "123456789"
      },
      {
        "label": "BANK_ACC",
        "box": [
          134,
          64,
          71,
          8
        ],
        "matched": "123456789"
      },
      {
        "label": "BANK_ACC",
        "box": [
          398,
          118,
          162,
          30
        ],
        "matched": "1164952208"
      },
      {
        "label": "BANK_ACC",
        "box": [
          214,
          152,
          69,
          8
        ],
        "matched": "123456768"
      },
      {
        "label": "BANK_ACC",
        "box": [
          134,
          64,
          71,
          8
        ],
        "matched": "123456789"
      },
      {
        "label": "BANK_ACC",
        "box": [
          134,
          64,
          71,
          8
        ],
        "matched": "123456789"
      },
      {
        "label": "BANK_ACC",
        "box": [
          134,
          64,
          71,
          8
        ],
        "matched": "123456789"
      },
      {
        "label": "BANK_ACC",
        "box": [
          402,
          272,
          162,
          30
        ],
        "matched": "1578706308"
      },
      {
        "label": "BANK_ACC",
        "box": [
          134,
          306,
          77,
          9
        ],
        "matched": "128456789"
      },
      {
        "label": "BANK_ACC",
        "box": [
          402,
          306,
          161,
          8
        ],
        "matched": "1104123801"
      },
      {
        "label": "INSURANCE_ID",
        "box": [
          0,
          0,
          0,
          0
        ],
        "matched": "member\nIDalpha"
      }
    ],
    "redacted": [
      {
        "label": "PHONE",
        "box": [
          241,
          74,
          81,
          31
        ],
        "matched": "2345676611"
      },
      {
        "label": "PHONE",
        "box": [
          398,
          118,
          162,
          30
        ],
        "matched": "1164952208"
      },
      {
        "label": "PHONE",
        "box": [
          402,
          272,
          162,
          30
        ],
        "matched": "1578706308"
      },
      {
        "label": "PHONE",
        "box": [
          402,
          306,
          161,
          8
        ],
        "matched": "1104123801"
      },
      {
        "label": "NPI",
        "box": [
          398,
          118,
          162,
          30
        ],
        "matched": "1164952208"
      },
      {
        "label": "NPI",
        "box": [
          402,
          272,
          162,
          30
        ],
        "matched": "1578706308"
      },
      {
        "label": "NPI",
        "box": [
          402,
          306,
          161,
          8
        ],
        "matched": "1104123801"
      },
      {
        "label": "DL_GENERIC",
        "box": [
          90,
          63,
          40,
          11
        ],
        "matched": "BCBSAK"
      },
      {
        "label": "DL_GENERIC",
        "box": [
          134,
          64,
          71,
          8
        ],
        "matched": "123456789"
      },
      {
        "label": "DL_GENERIC",
        "box": [
          104,
          74,
          38,
          31
        ],
        "matched": "BOBSAR"
      },
      {
        "label": "DL_GENERIC",
        "box": [
          241,
          74,
          81,
          31
        ],
        "matched": "XOM2345676611"
      },
      {
        "label": "DL_GENERIC",
        "box": [
          551,
          74,
          55,
          31
        ],
        "matched": "184150458"
      },
      {
        "label": "DL_GENERIC",
        "box": [
          97,
          96,
          30,
          30
        ],
        "matched": "BCBSFL"
      },
      {
        "label": "DL_GENERIC",
        "box": [
          222,
          96,
          68,
          30
        ],
        "matched": "XJBH12345678"
      },
      {
        "label": "DL_GENERIC",
        "box": [
          87,
          129,
          65,
          11
        ],
        "matched": "BCBSID"
      },
      {
        "label": "DL_GENERIC",
        "box": [
          131,
          129,
          74,
          11
        ],
        "matched": "XNE123456789"
      },
      {
        "label": "DL_GENERIC",
        "box": [
          209,
          130,
          74,
          8
        ],
        "matched": "SAW123456789"
      },
      {
        "label": "DL_GENERIC",
        "box": [
          398,
          118,
          162,
          30
        ],
        "matched": "1164952208"
      },
      {
        "label": "DL_GENERIC",
        "box": [
          92,
          151,
          63,
          11
        ],
        "matched": "BCBSIL"
      },
      {
        "label": "DL_GENERIC",
        "box": [
          54,
          174,
          49,
          8
        ],
        "matched": "MICHIGAN"
      },
      {
        "label": "DL_GENERIC",
        "box": [
          238,
          174,
          74,
          8
        ],
        "matched": "FMMO123456789"
      },
      {
        "label": "DL_GENERIC",
        "box": [
          102,
          196,
          39,
          8
        ],
        "matched": "BCESMT"
      },
      {
        "label": "DL_GENERIC",
        "box": [
          114,
          239,
          41,
          11
        ],
        "matched": "BOBSOK"
      },
      {
        "label": "DL_GENERIC",
        "box": [
          159,
          240,
          75,
          9
        ],
        "matched": "YUPT23456789"
      },
      {
        "label": "DL_GENERIC",
        "box": [
          238,
          240,
          71,
          8
        ],
        "matched": "YUAI23456789"
      },
      {
        "label": "DL_GENERIC",
        "box": [
          55,
          261,
          44,
          11
        ],
        "matched": "OREGON"
      },
      {
        "label": "DL_GENERIC",
        "box": [
          154,
          262,
          78,
          9
        ],
        "matched": "WCP123456789"
      },
      {
        "label": "DL_GENERIC",
        "box": [
          93,
          283,
          40,
          11
        ],
        "matched": "BOBSTX"
      },
      {
        "label": "DL_GENERIC",
        "box": [
          217,
          284,
          70,
          8
        ],
        "matched": "JEA123456789"
      },
      {
        "label": "DL_GENERIC",
        "box": [
          402,
          272,
          162,
          30
        ],
        "matched": "1578706308"
      },
      {
        "label": "DL_GENERIC",
        "box": [
          89,
          305,
          41,
          11
        ],
        "matched": "BOBSUT"
      },
      {
        "label": "DL_GENERIC",
        "box": [
          134,
          306,
          77,
          9
        ],
        "matched": "128456789"
      },
      {
        "label": "DL_GENERIC",
        "box": [
          402,
          306,
          161,
          8
        ],
        "matched": "1104123801"
      },
      {
        "label": "BANK_ACC",
        "box": [
          134,
          64,
          71,
          8
        ],
        "matched": "123456789"
      },
      {
        "label": "BANK_ACC",
        "box": [
          241,
          74,
          81,
          31
        ],
        "matched": "2345676611"
      },
      {
        "label": "BANK_ACC",
        "box": [
          551,
          74,
          55,
          31
        ],
        "matched": "184150458"
      },
      {
        "label": "BANK_ACC",
        "box": [
          134,
          64,
          71,
          8
        ],
        "matched": "123456789"
      },
      {
        "label": "BANK_ACC",
        "box": [
          134,
          64,
          71,
          8
        ],
        "matched": "123456789"
      },
      {
        "label": "BANK_ACC",
        "box": [
          398,
          118,
          162,
          30
        ],
        "matched": "1164952208"
      },
      {
        "label": "BANK_ACC",
        "box": [
          214,
          152,
          69,
          8
        ],
        "matched": "123456768"
      },
      {
        "label": "BANK_ACC",
        "box": [
          134,
          64,
          71,
          8
        ],
        "matched": "123456789"
      },
      {
        "label": "BANK_ACC",
        "box": [
          134,
          64,
          71,
          8
        ],
        "matched": "123456789"
      },
      {
        "label": "BANK_ACC",
        "box": [
          134,
          64,
          71,
          8
        ],
        "matched": "123456789"
      },
      {
        "label": "BANK_ACC",
        "box": [
          402,
          272,
          162,
          30
        ],
        "matched": "1578706308"
      },
      {
        "label": "BANK_ACC",
        "box": [
          134,
          306,
          77,
          9
        ],
        "matched": "128456789"
      },
      {
        "label": "BANK_ACC",
        "box": [
          402,
          306,
          161,
          8
        ],
        "matched": "1104123801"
      },
      {
        "label": "INSURANCE_ID",
        "box": [
          0,
          0,
          0,
          0
        ],
        "matched": "member\nIDalpha"
      }
    ],
    "mode": "blur",
    "timestamp": "20250903T121448",
    "page": ""
  }
]